translate_it/__init__.py
translate_it/__version__.py
translate_it/translate_it.py
translate_it/dictionaries/__init__.py
translate_it/dictionaries/youdao/__init__.py
translate_it-0.3.2.4.dist-info/METADATA
translate_it-0.3.2.4.dist-info/WHEEL
translate_it-0.3.2.4.dist-info/entry_points.txt
translate_it-0.3.2.4.dist-info/top_level.txt
translate_it-0.3.2.4.dist-info/RECORD
