Metadata-Version: 2.1
Name: translate-it
Version: 0.3.2.4
Summary: translate it for me.
Home-page: https://github.com/suadminwen/translate-it
Author: wen
Author-email: w_angzhiwen@163.com
License: UNKNOWN
Platform: UNKNOWN
Classifier: Programming Language :: Python :: 3.5
Classifier: Programming Language :: Python :: 3.6
Classifier: Programming Language :: Python :: 3.7
Classifier: Programming Language :: Python :: 3.8
Requires-Python: >=3.5
Requires-Dist: requests (>=2.22.0)
Requires-Dist: lxml (>=4.4.1)
Requires-Dist: cachelib
Requires-Dist: appdirs
